morse.v
module morse (
    in, out, reset, clk
);
    input in, reset, clk;
    output reg [7:0] out;

    parameter IDLE = 5'bxxxxx, E = 5'b00000, A = 5'b00001, T = 5'b00010, I = 5'b00100, S = 5'b00101, U = 5'b00110, N = 5'b01000, M = 5'b01001, G = 5'b01010, O = 5'b01100;
    reg [5:0] state, next_state;

    // Lógica Sequencial    
    always @(posedge clk) begin
        if (reset)
            state = IDLE;
        else
            state = next_state;        
    end
    
    // Lógica Combinacional de entrada
    always @(*) begin
        case (state)   // 1 -> ponto 0 -> traço
            IDLE: begin
                if (in)
                    next_state = E; // .
                else
                    next_state = T; // -
            end   
            E: begin
                if (in)
                    next_state = I; // ..
                else
                    next_state = A; // .-
            end  
            I: begin
                if(in)
                    next_state = S;
                else
                    next_state = U;
            end   
            T: begin
                if(in)
                    next_state = N;
                else
                    next_state = M;
            end   
            M: begin
                if(in)
                    next_state = G;
                else
                    next_state = O;
            end             
            default: next_state = IDLE;
        endcase
        
    end

    // Lógica Combinacional de saída
    always @(*) begin
        case (state)
            IDLE: out = 8'h00;
            E: out = 8'h45;
            T: out = 8'h54;
            A: out = 8'h42;
            I: out = 8'h49;  
            S: out = 8'h53;
            U: out = 8'h55;    
            N: out = 8'h4E;
            M: out = 8'h4D;
            G: out = 8'h47;
            O: out = 8'h4F;
            default: next_state = IDLE;
        endcase
    end
endmodule

morse_tb.v
`timescale 10ns/1ns
`include "morse.v"

module morse_tb;


    reg in, reset, clk;
    wire [7:0] out;
    morse uut(in, out, reset, clk);

    initial begin
        $dumpfile("morse.vcd");
        $dumpvars(0, morse_tb);

        reset = 1; #15 reset = 0;
        in = 1; #60 reset = 1; #30;

        $finish;
    end

    initial begin
        clk = 0;
        forever #10 clk = ~clk;
    end
    

endmodule

morse.vcd
$date
	Mon Nov 18 09:29:25 2024
$end
$version
	Icarus Verilog
$end
$timescale
	1ns
$end
$scope module morse_tb $end
$var wire 8 ! out [7:0] $end
$var reg 1 " clk $end
$var reg 1 # in $end
$var reg 1 $ reset $end
$scope module uut $end
$var wire 1 " clk $end
$var wire 1 # in $end
$var wire 1 $ reset $end
$var parameter 5 % A $end
$var parameter 5 & E $end
$var parameter 5 ' G $end
$var parameter 5 ( I $end
$var parameter 5 ) IDLE $end
$var parameter 5 * M $end
$var parameter 5 + N $end
$var parameter 5 , O $end
$var parameter 5 - S $end
$var parameter 5 . T $end
$var parameter 5 / U $end
$var reg 6 0 next_state [5:0] $end
$var reg 8 1 out [7:0] $end
$var reg 6 2 state [5:0] $end
$upscope $end
$upscope $end
$enddefinitions $end
$comment Show the parameter values. $end
$dumpall
b110 /
b10 .
b101 -
b1100 ,
b1000 +
b1001 *
bx )
b100 (
b1010 '
b0 &
b1 %
$end
#0
$dumpvars
bx 2
bx 1
bx 0
1$
x#
0"
bx !
$end
#100
b0 !
b0 1
b10 0
b0xxxxx 2
1"
#150
b0 0
1#
0$
#200
0"
#300
b1000101 !
b1000101 1
b100 0
b0 2
1"
#400
0"
#500
b1001001 !
b1001001 1
b101 0
b100 2
1"
#600
0"
#700
b1010011 !
b1010011 1
b0xxxxx 0
b101 2
1"
#750
1$
#800
0"
#900
b0 !
b0 1
b0 0
b0xxxxx 2
1"
